[
  {
    "name": ".gitkeep",
    "relPath": ".gitkeep",
    "size": 0,
    "url": "/uploads/.gitkeep"
  },
  {
    "name": "Comentarios de la dirección.pdf",
    "relPath": "Salva al mundo pero no le digas a nadie/Comentarios de la Dirección/Comentarios de la dirección.pdf",
    "size": 73788,
    "url": "/uploads/Salva%20al%20mundo%20pero%20no%20le%20digas%20a%20nadie/Comentarios%20de%20la%20Direcci%C3%B3n/Comentarios%20de%20la%20direcci%C3%B3n.pdf"
  },
  {
    "name": "Diseño de locaciones.pdf",
    "relPath": "Salva al mundo pero no le digas a nadie/Diseño de locaciones/Diseño de locaciones.pdf",
    "size": 1778560,
    "url": "/uploads/Salva%20al%20mundo%20pero%20no%20le%20digas%20a%20nadie/Dise%C3%B1o%20de%20locaciones/Dise%C3%B1o%20de%20locaciones.pdf"
  },
  {
    "name": "Diseño de personajes.pdf",
    "relPath": "Salva al mundo pero no le digas a nadie/Diseño de personajes/Diseño de personajes.pdf",
    "size": 2518545,
    "url": "/uploads/Salva%20al%20mundo%20pero%20no%20le%20digas%20a%20nadie/Dise%C3%B1o%20de%20personajes/Dise%C3%B1o%20de%20personajes.pdf"
  },
  {
    "name": "Lore.pdf",
    "relPath": "Salva al mundo pero no le digas a nadie/Lore/Lore.pdf",
    "size": 780222,
    "url": "/uploads/Salva%20al%20mundo%20pero%20no%20le%20digas%20a%20nadie/Lore/Lore.pdf"
  }
]